Metadata-Version: 1.0
Name: mygaussbino
Version: 0.1
Summary: Gaussian and Binomial distributions
Home-page: UNKNOWN
Author: Poorvika A
Author-email: poorvikanaidu18@gmail.com
License: UNKNOWN
Platform: UNKNOWN
